silent/__init__.py
silent/client.py
silent/silent.py
silent/wrapper.py
silent-0.1a1.dist-info/DESCRIPTION.rst
silent-0.1a1.dist-info/METADATA
silent-0.1a1.dist-info/RECORD
silent-0.1a1.dist-info/WHEEL
silent-0.1a1.dist-info/entry_points.txt
silent-0.1a1.dist-info/metadata.json
silent-0.1a1.dist-info/top_level.txt
