Metadata-Version: 2.0
Name: silent
Version: 0.1a1
Summary: A commandline client for file.io
Home-page: https://github.com/vinyasns/silent
Author: Vinyas N S
Author-email: vinyasns@gmail.com
License: GPLv3
Keywords: file.io,commandline,utilities,anonymous
Platform: UNKNOWN
Classifier: Development Status :: 3 - Alpha
Classifier: Environment :: Console
Classifier: Topic :: Utilities
Classifier: Intended Audience :: Developers
Classifier: License :: OSI Approved :: GNU General Public License v3 or later (GPLv3+)
Classifier: Natural Language :: English
Classifier: Operating System :: POSIX :: Linux
Classifier: Programming Language :: Python :: 3
Requires-Python: >=3
Requires-Dist: clint
Requires-Dist: python-magic
Requires-Dist: requests-toolbelt
